pydecensooru/__about__.py
pydecensooru/__init__.py
pydecensooru/main.py
pydecensooru-0.2.0.dist-info/METADATA
pydecensooru-0.2.0.dist-info/RECORD
pydecensooru-0.2.0.dist-info/WHEEL
pydecensooru-0.2.0.dist-info/top_level.txt
