Metadata-Version: 2.1
Name: pydecensooru
Version: 0.2.0
Summary: Danbooru post decensoring for Python
Home-page: https://github.com/mirukan/pydecensooru
Author: miruka
Author-email: miruka@disroot.org
License: LGPLv3
Keywords: better booru danbooru gold member bypass decensooru uncensor banned artist lunakit lunafind
Platform: UNKNOWN
Classifier: Development Status :: 3 - Alpha
Classifier: Intended Audience :: Developers
Classifier: Topic :: Internet
Classifier: License :: OSI Approved :: GNU Lesser General Public License v3 or later (LGPLv3+)
Classifier: Programming Language :: Python :: 3
Classifier: Programming Language :: Python :: 3 :: Only
Classifier: Programming Language :: Python :: 3.6
Classifier: Programming Language :: Python :: 3.7
Classifier: Natural Language :: English
Requires-Python: >=3.6, <4
Requires-Dist: appdirs
Requires-Dist: atomicfile
Requires-Dist: requests
